syllapy/__init__.py
syllapy/data.json
syllapy/data_loader.py
syllapy-0.7.1.dist-info/LICENSE
syllapy-0.7.1.dist-info/WHEEL
syllapy-0.7.1.dist-info/METADATA
syllapy-0.7.1.dist-info/RECORD
