Metadata-Version: 2.1
Name: syllapy
Version: 0.7.1
Summary: Calculate syllable counts for English words.
Home-page: https://github.com/mholtzscher/syllapy
License: MIT
Keywords: syllables,nlp
Author: Michael Holtzscher
Author-email: mholtz@protonmail.com
Requires-Python: >=3.6,<4.0
Classifier: License :: OSI Approved :: MIT License
Classifier: Programming Language :: Python :: 3
Classifier: Programming Language :: Python :: 3.6
Classifier: Programming Language :: Python :: 3.7
Requires-Dist: ujson (>=1.35,<2.0)
Project-URL: Repository, https://github.com/mholtzscher/syllapy
